claude_session_manager_mcp/__init__.py
claude_session_manager_mcp/models.py
claude_session_manager_mcp/server.py
claude_session_manager_mcp/web/__init__.py
claude_session_manager_mcp/web/__main__.py
claude_session_manager_mcp/web/app.py
claude_session_manager_mcp/web/devserver.py
claude_session_manager_mcp/web/templates/index.html
claude_session_manager_mcp-0.1.5.dist-info/METADATA
claude_session_manager_mcp-0.1.5.dist-info/WHEEL
claude_session_manager_mcp-0.1.5.dist-info/entry_points.txt
claude_session_manager_mcp-0.1.5.dist-info/RECORD
