Metadata-Version: 2.4
Name: claude-session-manager-mcp
Version: 0.1.5
Summary: MCP server for managing Claude Code conversation sessions
Author: drumrobot43@gmail.com
License: MIT
Keywords: ai,claude,claude-code,conversation,mcp,mcp-server,session-manager
Classifier: Development Status :: 4 - Beta
Classifier: Intended Audience :: Developers
Classifier: License :: OSI Approved :: MIT License
Classifier: Programming Language :: Python :: 3
Classifier: Programming Language :: Python :: 3.10
Classifier: Programming Language :: Python :: 3.11
Classifier: Programming Language :: Python :: 3.12
Requires-Python: >=3.10
Requires-Dist: flask-cors>=4.0.0
Requires-Dist: flask>=3.0.0
Requires-Dist: mcp>=1.0.0
